nucleotide_archive_mcp/__init__.py
nucleotide_archive_mcp/config.py
nucleotide_archive_mcp/ena_client.py
nucleotide_archive_mcp/main.py
nucleotide_archive_mcp/mcp.py
nucleotide_archive_mcp/utils.py
nucleotide_archive_mcp/tools/__init__.py
nucleotide_archive_mcp/tools/downloads.py
nucleotide_archive_mcp/tools/metadata.py
nucleotide_archive_mcp/tools/publications.py
nucleotide_archive_mcp/tools/search_studies.py
nucleotide_archive_mcp/tools/study_details.py
nucleotide_archive_mcp-0.0.2.dist-info/METADATA
nucleotide_archive_mcp-0.0.2.dist-info/WHEEL
nucleotide_archive_mcp-0.0.2.dist-info/entry_points.txt
nucleotide_archive_mcp-0.0.2.dist-info/licenses/LICENSE
nucleotide_archive_mcp-0.0.2.dist-info/RECORD
