Metadata-Version: 2.4
Name: nucleotide-archive-mcp
Version: 0.0.2
Summary: MCP server for searching European Nucleotide Archive (ENA) datasets. Find RNA-seq studies, retrieve metadata, and discover related publications to validate research hypotheses.
Project-URL: Documentation, https://nucleotide_archive_mcp.readthedocs.io/
Project-URL: Homepage, https://github.com/biocontext-ai/nucleotide_archive_mcp
Project-URL: Source, https://github.com/biocontext-ai/nucleotide_archive_mcp
Author: Malte Kuehl
Maintainer-email: Malte Kuehl <malte.kuehl@clin.au.dk>
License: 
License-File: LICENSE
Classifier: Programming Language :: Python :: 3 :: Only
Classifier: Programming Language :: Python :: 3.11
Classifier: Programming Language :: Python :: 3.12
Classifier: Programming Language :: Python :: 3.13
Requires-Python: >=3.11
Requires-Dist: click
Requires-Dist: fastmcp
Requires-Dist: httpx==0.28.*
Provides-Extra: dev
Requires-Dist: pre-commit; extra == 'dev'
Requires-Dist: twine>=4.0.2; extra == 'dev'
Provides-Extra: doc
Requires-Dist: docutils!=0.18.*,!=0.19.*,>=0.8; extra == 'doc'
Requires-Dist: ipykernel; extra == 'doc'
Requires-Dist: ipython; extra == 'doc'
Requires-Dist: myst-nb>=1.1; extra == 'doc'
Requires-Dist: pandas; extra == 'doc'
Requires-Dist: setuptools; extra == 'doc'
Requires-Dist: sphinx-autoapi; extra == 'doc'
Requires-Dist: sphinx-book-theme>=1; extra == 'doc'
Requires-Dist: sphinx-copybutton; extra == 'doc'
Requires-Dist: sphinx-tabs; extra == 'doc'
Requires-Dist: sphinx>=8.1; extra == 'doc'
Requires-Dist: sphinxext-opengraph; extra == 'doc'
Provides-Extra: test
Requires-Dist: coverage; extra == 'test'
Requires-Dist: pytest; extra == 'test'
Requires-Dist: pytest-asyncio; extra == 'test'
